niwrap_fastsurfer/fastsurfer/__init__.py
niwrap_fastsurfer/fastsurfer/run_fastsurfer_sh.py
niwrap_fastsurfer-0.8.3.dist-info/WHEEL
niwrap_fastsurfer-0.8.3.dist-info/METADATA
niwrap_fastsurfer-0.8.3.dist-info/RECORD
